<Properties StartupConfiguration="{5FA6E21B-A52E-4287-A31A-D0886DCFA21B}|Default" GitUserInfo="UsingGIT">
  <MonoDevelop.Ide.Workbench ActiveDocument="StemmonsCentralToGo Status">
    <Files>
      <File FileName="StemmonsMobile/StemmonsMobile/Views/HtmlLabelConverter.cs" Line="80" Column="30" />
      <File FileName="StemmonsMobile/StemmonsMobile/Views/Cases/ViewCasePage.xaml" Line="352" Column="1" />
      <File FileName="StemmonsMobile/StemmonsMobile/Views/Cases/ViewCasePage.xaml.cs" Line="1422" Column="78" />
      <File FileName="StemmonsMobile/StemmonsMobile/Commonfiles/Functions.cs" Line="97" Column="41" />
      <File FileName="StemmonsMobile/StemmonsMobile.iOS/Info.plist" />
      <File FileName="StemmonsCentralToGo Status" />
    </Files>
  </MonoDevelop.Ide.Workbench>
  <MonoDevelop.Ide.Workspace ActiveConfiguration="AppStore|iPhone" />
  <MonoDevelop.Ide.DebuggingService.Breakpoints>
    <BreakpointStore />
  </MonoDevelop.Ide.DebuggingService.Breakpoints>
  <MonoDevelop.Ide.ItemProperties.StemmonsMobile.Android PreferredExecutionTarget="Android.Android_Accelerated_Oreo" AndroidDesignerPreferredTheme="Theme.DeviceDefault.NoActionBar.Fullscreen" />
  <MonoDevelop.Ide.DebuggingService.PinnedWatches />
  <MultiItemStartupConfigurations />
  <MonoDevelop.Ide.ItemProperties.StemmonsMobile.iOS PreferredExecutionTarget="MonoDevelop.IPhone.IPhoneDeviceTarget.bbfc9da971ed0bc730359a50bec3bee68380755a" automaticSigning="False" />
</Properties>